clearvision/__init__.py
clearvision/__main__.py
clearvision/cleaning.py
clearvision/detection.py
clearvision/ocr.py
clearvision/imageproc/__init__.py
clearvision/imageproc/toolkit.py
clearvision/models/frozen_east_text_detection.pb
clearvision-0.3.2.dist-info/LICENSE.txt
clearvision-0.3.2.dist-info/METADATA
clearvision-0.3.2.dist-info/WHEEL
clearvision-0.3.2.dist-info/top_level.txt
clearvision-0.3.2.dist-info/RECORD
