Metadata-Version: 2.1
Name: clearvision
Version: 0.3.2
Summary: Add a short description here!
Home-page: https://github.com/pyscaffold/pyscaffold/
Author: Chris Maikos
Author-email: chmaikos@gmail.com
License: MIT
Project-URL: Documentation, https://pyscaffold.org/
Platform: any
Classifier: Development Status :: 4 - Beta
Classifier: Programming Language :: Python
Requires-Python: >=3.9
License-File: LICENSE.txt
Requires-Dist: imutils >=0.5.4
Requires-Dist: image-ocr >=0.0.3
Requires-Dist: numpy >=1.24.0
Requires-Dist: skimage-image ; python_version < "3.8"
Requires-Dist: tensorflow-cpu ; python_version < "3.8"
Requires-Dist: importlib-metadata ; python_version < "3.8"
Provides-Extra: testing
Requires-Dist: setuptools ; extra == 'testing'
Requires-Dist: pytest ; extra == 'testing'
Requires-Dist: pytest-cov ; extra == 'testing'
